django_fias-1.2.2.dist-info/DESCRIPTION.rst
django_fias-1.2.2.dist-info/METADATA
django_fias-1.2.2.dist-info/RECORD
django_fias-1.2.2.dist-info/WHEEL
django_fias-1.2.2.dist-info/metadata.json
django_fias-1.2.2.dist-info/top_level.txt
fias/__init__.py
fias/admin.py
fias/compat.py
fias/config.py
fias/forms.py
fias/routers.py
fias/urls.py
fias/version.py
fias/views.py
fias/weights.py
fias/fields/__init__.py
fias/fields/address.py
fias/fields/uuid.py
fias/importer/__init__.py
fias/importer/commands.py
fias/importer/filters.py
fias/importer/indexes.py
fias/importer/loader.py
fias/importer/log.py
fias/importer/signals.py
fias/importer/timer.py
fias/importer/validators.py
fias/importer/version.py
fias/importer/source/__init__.py
fias/importer/source/archive.py
fias/importer/source/directory.py
fias/importer/source/tablelist.py
fias/importer/source/wrapper.py
fias/importer/table/__init__.py
fias/importer/table/dbf.py
fias/importer/table/table.py
fias/importer/table/xml.py
fias/locale/ru/LC_MESSAGES/django.mo
fias/locale/ru/LC_MESSAGES/django.po
fias/management/__init__.py
fias/management/commands/__init__.py
fias/management/commands/fias.py
fias/management/commands/fias_duplicates.py
fias/management/commands/fias_suggest.py
fias/management/commands/fiasinfo.py
fias/management/utils/__init__.py
fias/management/utils/weights.py
fias/migrations/0001_initial.py
fias/migrations/0002_auto_20160817_0234.py
fias/migrations/0003_actstat_centerst_curentst_eststat_hststat_intvstat_ndoctype_operstat_strstat.py
fias/migrations/0004_auto_20160824_1003.py
fias/migrations/0005_load_stats_data.py
fias/migrations/0006_add_fks_to_addrobj.py
fias/migrations/0007_add_fks_to_house.py
fias/migrations/0008_add_fks_to_houseint.py
fias/migrations/0009_add_fks_to_normdoc.py
fias/migrations/0010_room_stead.py
fias/migrations/0011_default_fks_values.py
fias/migrations/0012_field_descriptions_and_more_fks.py
fias/migrations/0013_auto_20160825_0524.py
fias/migrations/0014_addrobj_plancode.py
fias/migrations/0015_auto_20161224_0054.py
fias/migrations/__init__.py
fias/models/__init__.py
fias/models/address.py
fias/models/addrobj.py
fias/models/common.py
