Metadata-Version: 2.0
Name: django-fias
Version: 1.2.2
Summary: FIAS Django integration
Home-page: https://github.com/Yuego/django-fias
Author: Artem Vlasov
Author-email: root@proscript.ru
License: MIT license
Download-URL: https://github.com/Yuego/django-fias/archive/1.2.2.tar.gz
Platform: UNKNOWN
Classifier: Development Status :: 4 - Beta
Classifier: Intended Audience :: Developers
Classifier: Intended Audience :: Science/Research
Classifier: License :: OSI Approved :: MIT License
Classifier: Natural Language :: Russian
Classifier: Programming Language :: Python
Classifier: Programming Language :: Python :: 2
Classifier: Programming Language :: Python :: 2.7
Classifier: Programming Language :: Python :: 3
Classifier: Programming Language :: Python :: 3.4
Classifier: Programming Language :: Python :: 3.5
Classifier: Topic :: Software Development :: Libraries :: Python Modules
Requires-Dist: dbfread (>=2.0.5)
Requires-Dist: django (<1.11,>=1.8)
Requires-Dist: django-select2 (>=5.3.0)
Requires-Dist: lxml
Requires-Dist: mysqlclient (!=1.3.8)
Requires-Dist: progress
Requires-Dist: rarfile
Requires-Dist: six
Requires-Dist: suds-jurko (>=0.6)
Requires-Dist: unrar
Requires-Dist: zeep (>=0.17.0)
